acapelladb/BatchBase.py
acapelladb/BatchManual.py
acapelladb/Cursor.py
acapelladb/Entry.py
acapelladb/IndexField.py
acapelladb/PartitionIndex.py
acapelladb/Session.py
acapelladb/Transaction.py
acapelladb/TransactionContext.py
acapelladb/Tree.py
acapelladb/__init__.py
acapelladb/utils/__init__.py
acapelladb/utils/assertion.py
acapelladb/utils/collections.py
acapelladb/utils/errors.py
acapelladb/utils/http.py
acapelladb-0.3.8.dist-info/METADATA
acapelladb-0.3.8.dist-info/WHEEL
acapelladb-0.3.8.dist-info/top_level.txt
acapelladb-0.3.8.dist-info/RECORD
