Metadata-Version: 2.1
Name: acapelladb
Version: 0.3.8
Summary: Python client for AcapellaDB database
Home-page: https://github.com/AcapellaSoft/AcapellaDBClient-py
Author: Acapella Soft
License: MIT
Platform: UNKNOWN
Classifier: Development Status :: 3 - Alpha
Classifier: License :: OSI Approved :: MIT License
Classifier: Programming Language :: Python :: 3.6
Requires-Dist: aiohttp (==3.4.4)
Requires-Dist: requests (==2.20.0)
